LogColorHelper/LogColorHelper.py
LogColorHelper/__init__.py
LogColorHelper_jingle1267-0.1.8.dist-info/LICENSE
LogColorHelper_jingle1267-0.1.8.dist-info/METADATA
LogColorHelper_jingle1267-0.1.8.dist-info/WHEEL
LogColorHelper_jingle1267-0.1.8.dist-info/top_level.txt
LogColorHelper_jingle1267-0.1.8.dist-info/RECORD
